{
  "name": "SnapTagsView",
  "version": "0.6.3",
  "summary": "Tag buttons, a tag bar and UISearchBar with tags",
  "description": "",
  "homepage": "https://github.com/skylib/SnapTagsView",
  "license": {
    "type": "BSD",
    "file": "LICENSE"
  },
  "authors": [
    "Niklas Saers"
  ],
  "social_media_url": "http://twitter.com/snapsale_com",
  "source": {
    "git": "https://github.com/skylib/SnapTagsView.git",
    "commit": "fbe9a47c9b553abf48b1e688a30c166ad99e135c"
  },
  "platforms": {
    "ios": 8.0
  },
  "source_files": ["SnapTagsView/*.swift"],
  "resources": [ "SnapTagsView/*.xib", "SnapTagsView/DefaultImages.xcassets"],
  "frameworks": "Foundation",
  "exclude_files": "Example*",
  "dependencies": {
	  "NSLayoutConstraint+ExpressionFormat": [ ],
	  "KTCenterFlowLayout": [ ],
	  "UICollectionViewLeftAlignedLayout": [ ],
	  "UICollectionViewRightAlignedLayout": [ ]
  }
}
